caelum_sys/__init__.py
caelum_sys/ai_agent.py
caelum_sys/ai_integration.py
caelum_sys/auto_import_plugins.py
caelum_sys/cli.py
caelum_sys/core_actions.py
caelum_sys/executor.py
caelum_sys/parser.py
caelum_sys/registry.py
caelum_sys/system.py
caelum_sys/plugins/__init__.py
caelum_sys/plugins/advanced_vision.py
caelum_sys/plugins/caelum_control.py
caelum_sys/plugins/data_processing.py
caelum_sys/plugins/date_time.py
caelum_sys/plugins/dev_assistant_setup.py
caelum_sys/plugins/dev_tools.py
caelum_sys/plugins/file_info.py
caelum_sys/plugins/file_management.py
caelum_sys/plugins/git_integration.py
caelum_sys/plugins/help_system.py
caelum_sys/plugins/input_control.py
caelum_sys/plugins/math_calculations.py
caelum_sys/plugins/media_controls.py
caelum_sys/plugins/misc_commands.py
caelum_sys/plugins/monitoring_tools.py
caelum_sys/plugins/network_tools.py
caelum_sys/plugins/process_tools.py
caelum_sys/plugins/quick_notes.py
caelum_sys/plugins/screen_watching.py
caelum_sys/plugins/screenshot_tools.py
caelum_sys/plugins/system_utils.py
caelum_sys/plugins/text_clipboard.py
caelum_sys/plugins/web_api.py
caelum_sys/plugins/windows_tools.py
caelum_sys-0.4.0.dist-info/licenses/LICENSE
caelum_sys-0.4.0.dist-info/METADATA
caelum_sys-0.4.0.dist-info/WHEEL
caelum_sys-0.4.0.dist-info/entry_points.txt
caelum_sys-0.4.0.dist-info/top_level.txt
caelum_sys-0.4.0.dist-info/RECORD
