Metadata-Version: 2.4
Name: caelum-sys
Version: 0.4.0
Summary: AI-enhanced system automation toolkit with HIGH-PERFORMANCE vision - 135+ commands, MSS/OpenCV/Tesseract integration, OpenAI/Anthropic/Ollama support
Author: Joshua Wells
License-Expression: MIT
Project-URL: Homepage, https://github.com/BlackBeardJW/caelum-sys
Project-URL: Repository, https://github.com/BlackBeardJW/caelum-sys
Project-URL: Issues, https://github.com/BlackBeardJW/caelum-sys/issues
Project-URL: Documentation, https://github.com/BlackBeardJW/caelum-sys/blob/main/AI_QUICKSTART.md
Keywords: automation,system,scripting,ai,natural-language,openai,anthropic,ollama,local-models,assistant,agent,chatbot
Classifier: Development Status :: 4 - Beta
Classifier: Intended Audience :: Developers
Classifier: Operating System :: OS Independent
Classifier: Programming Language :: Python :: 3
Classifier: Programming Language :: Python :: 3.9
Classifier: Programming Language :: Python :: 3.10
Classifier: Programming Language :: Python :: 3.11
Classifier: Programming Language :: Python :: 3.12
Classifier: Programming Language :: Python :: 3.13
Classifier: Topic :: System :: Shells
Classifier: Topic :: Software Development :: Libraries :: Python Modules
Classifier: Topic :: System :: Systems Administration
Classifier: Topic :: Scientific/Engineering :: Artificial Intelligence
Classifier: Topic :: Software Development :: Libraries :: Application Frameworks
Classifier: Topic :: Utilities
Requires-Python: >=3.9
License-File: LICENSE
Requires-Dist: psutil
Requires-Dist: pyautogui
Requires-Dist: requests
Requires-Dist: pillow
Requires-Dist: pyperclip
Requires-Dist: pytz
Requires-Dist: python-dateutil
Requires-Dist: mss>=9.0.1
Requires-Dist: opencv-python>=4.8.0
Requires-Dist: pytesseract>=0.3.10
Requires-Dist: numpy>=1.24.0
Provides-Extra: openai
Requires-Dist: openai>=1.0.0; extra == "openai"
Provides-Extra: anthropic
Requires-Dist: anthropic>=0.18.0; extra == "anthropic"
Provides-Extra: ai
Requires-Dist: openai>=1.0.0; extra == "ai"
Requires-Dist: anthropic>=0.18.0; extra == "ai"
Provides-Extra: vision
Requires-Dist: mss>=9.0.1; extra == "vision"
Requires-Dist: opencv-python>=4.8.0; extra == "vision"
Requires-Dist: pytesseract>=0.3.10; extra == "vision"
Requires-Dist: numpy>=1.24.0; extra == "vision"
Provides-Extra: dev
Requires-Dist: pytest; extra == "dev"
Requires-Dist: black; extra == "dev"
Requires-Dist: isort; extra == "dev"
Requires-Dist: mypy; extra == "dev"
Requires-Dist: types-requests; extra == "dev"
Requires-Dist: types-pytz; extra == "dev"
Requires-Dist: types-python-dateutil; extra == "dev"
Dynamic: license-file
